_flake8_tergeo/__init__.py
_flake8_tergeo/ast_util.py
_flake8_tergeo/base.py
_flake8_tergeo/flake8_types.py
_flake8_tergeo/global_options.py
_flake8_tergeo/hacks.py
_flake8_tergeo/interfaces.py
_flake8_tergeo/own_base.py
_flake8_tergeo/registry.py
_flake8_tergeo/type_definitions.py
_flake8_tergeo/util.py
_flake8_tergeo/wrapper_base.py
_flake8_tergeo/checks/__init__.py
_flake8_tergeo/checks/ast_assert.py
_flake8_tergeo/checks/ast_assign.py
_flake8_tergeo/checks/ast_bin_op.py
_flake8_tergeo/checks/ast_call.py
_flake8_tergeo/checks/ast_class_def.py
_flake8_tergeo/checks/ast_dict.py
_flake8_tergeo/checks/ast_except_handler.py
_flake8_tergeo/checks/ast_for.py
_flake8_tergeo/checks/ast_func_def.py
_flake8_tergeo/checks/ast_import.py
_flake8_tergeo/checks/ast_lambda.py
_flake8_tergeo/checks/ast_name_or_attribute.py
_flake8_tergeo/checks/ast_raise.py
_flake8_tergeo/checks/ast_str.py
_flake8_tergeo/checks/ast_subscript.py
_flake8_tergeo/checks/dev_comments.py
_flake8_tergeo/checks/docstyle.py
_flake8_tergeo/checks/file_tokens.py
_flake8_tergeo/checks/filename.py
_flake8_tergeo/checks/ftp115_invisible_chars.txt
_flake8_tergeo/checks/lines.py
_flake8_tergeo/checks/log_lint.py
_flake8_tergeo/checks/parens.py
_flake8_tergeo/checks/requirements.py
_flake8_tergeo/checks/shared.py
_flake8_tergeo/checks/wrappers.py
flake8_tergeo-25.12.19.1.dist-info/licenses/LICENSE
flake8_tergeo-25.12.19.1.dist-info/METADATA
flake8_tergeo-25.12.19.1.dist-info/WHEEL
flake8_tergeo-25.12.19.1.dist-info/entry_points.txt
flake8_tergeo-25.12.19.1.dist-info/top_level.txt
flake8_tergeo-25.12.19.1.dist-info/RECORD
