Metadata-Version: 2.4
Name: flake8-tergeo
Version: 25.12.19.1
Summary: flake8 plugin which keeps your code clean and tidy
Author-email: Kai Harder <kai.harder@sap.com>
License-Expression: Apache-2.0
Project-URL: Changelog, https://github.com/SAP/flake8-tergeo/blob/main/CHANGELOG.md
Project-URL: Issue Tracker, https://github.com/SAP/flake8-tergeo/issues
Keywords: flake8,plugin,quality,linter
Classifier: Development Status :: 5 - Production/Stable
Classifier: Environment :: Plugins
Classifier: Framework :: Flake8
Classifier: Intended Audience :: Developers
Classifier: Natural Language :: English
Classifier: Operating System :: OS Independent
Classifier: Programming Language :: Python :: 3
Classifier: Programming Language :: Python :: 3 :: Only
Classifier: Programming Language :: Python :: 3.10
Classifier: Programming Language :: Python :: 3.11
Classifier: Programming Language :: Python :: 3.12
Classifier: Programming Language :: Python :: 3.13
Classifier: Programming Language :: Python :: 3.14
Classifier: Topic :: Software Development :: Quality Assurance
Classifier: Typing :: Typed
Requires-Python: <4,>=3.10
License-File: LICENSE
Requires-Dist: flake8<9,>=7
Requires-Dist: typing-extensions~=4.4
Requires-Dist: flake8-comprehensions==3.17.0
Requires-Dist: flake8-bugbear==25.11.29
Requires-Dist: flake8-builtins==3.1.0
Requires-Dist: flake8-simplify==0.22.0
Requires-Dist: flake8-pytest-style==2.2.0
Requires-Dist: flake8-typing-imports==1.17.0
Requires-Dist: packaging>=24
Requires-Dist: dependency_groups~=1.3
Requires-Dist: tomli~=2.2; python_version < "3.11"
Dynamic: license-file
